odoo/addons/hr_timesheet_employee_analytic_tag/README.rst
odoo/addons/hr_timesheet_employee_analytic_tag/__init__.py
odoo/addons/hr_timesheet_employee_analytic_tag/__manifest__.py
odoo/addons/hr_timesheet_employee_analytic_tag/i18n/es.po
odoo/addons/hr_timesheet_employee_analytic_tag/i18n/hr_timesheet_employee_analytic_tag.pot
odoo/addons/hr_timesheet_employee_analytic_tag/i18n/it.po
odoo/addons/hr_timesheet_employee_analytic_tag/i18n/pt_BR.po
odoo/addons/hr_timesheet_employee_analytic_tag/models/__init__.py
odoo/addons/hr_timesheet_employee_analytic_tag/models/account_analytic_line.py
odoo/addons/hr_timesheet_employee_analytic_tag/models/hr_employee.py
odoo/addons/hr_timesheet_employee_analytic_tag/readme/CONFIGURE.md
odoo/addons/hr_timesheet_employee_analytic_tag/readme/CONTRIBUTORS.md
odoo/addons/hr_timesheet_employee_analytic_tag/readme/DESCRIPTION.md
odoo/addons/hr_timesheet_employee_analytic_tag/readme/USAGE.md
odoo/addons/hr_timesheet_employee_analytic_tag/static/description/icon.png
odoo/addons/hr_timesheet_employee_analytic_tag/static/description/index.html
odoo/addons/hr_timesheet_employee_analytic_tag/tests/__init__.py
odoo/addons/hr_timesheet_employee_analytic_tag/tests/test_hr_timesheet_employee_analytic_tag.py
odoo/addons/hr_timesheet_employee_analytic_tag/views/hr_employee_view.xml
odoo_addon_hr_timesheet_employee_analytic_tag-17.0.1.0.0.2.dist-info/METADATA
odoo_addon_hr_timesheet_employee_analytic_tag-17.0.1.0.0.2.dist-info/WHEEL
odoo_addon_hr_timesheet_employee_analytic_tag-17.0.1.0.0.2.dist-info/top_level.txt
odoo_addon_hr_timesheet_employee_analytic_tag-17.0.1.0.0.2.dist-info/RECORD
